{
    "1": 153,
    "10": 233,
    "11": 306,
    "12": 231,
    "13": 367,
    "14": 457,
    "15": 210,
    "16": 521,
    "17": 368,
    "18": 817,
    "19": 426,
    "2": 132,
    "20": 368,
    "21": 613,
    "22": 1248,
    "23": 662,
    "24": 990,
    "25": 527,
    "26": 907,
    "27": 1124,
    "28": 1285,
    "29": 1899,
    "3": 191,
    "30": 1159,
    "31": 1274,
    "32": 2085,
    "33": 2253,
    "34": 1818,
    "35": 1579,
    "36": 1709,
    "37": 2140,
    "38": 2136,
    "39": 2669,
    "4": 177,
    "40": 1491,
    "41": 3952,
    "42": 5881,
    "43": 6446,
    "44": 5512,
    "45": 4874,
    "46": 16840,
    "47": 20697,
    "48": 12279,
    "49": 11660,
    "5": 89,
    "50": 11410,
    "6": 180,
    "7": 184,
    "8": 185,
    "9": 115,
    "average": 2696.58
}