{
    "1": 37,
    "10": 54,
    "11": 77,
    "12": 331,
    "13": 215,
    "14": 320,
    "15": 244,
    "16": 353,
    "17": 223,
    "18": 518,
    "19": 223,
    "2": 35,
    "20": 429,
    "21": 401,
    "22": 1283,
    "23": 444,
    "24": 1102,
    "25": 642,
    "26": 696,
    "27": 1428,
    "28": 1345,
    "29": 1318,
    "3": 69,
    "30": 1436,
    "31": 1876,
    "32": 2128,
    "33": 2244,
    "34": 1856,
    "35": 1266,
    "36": 1518,
    "37": 2770,
    "38": 2178,
    "39": 2412,
    "4": 44,
    "40": 1761,
    "41": 5143,
    "42": 3561,
    "43": 4260,
    "44": 5011,
    "45": 4980,
    "46": 12393,
    "47": 14854,
    "48": 12309,
    "49": 13511,
    "5": 55,
    "50": 13108,
    "6": 46,
    "7": 49,
    "8": 70,
    "9": 67,
    "average": 2453.86
}