{
    "job1": 0,
    "job10": 0,
    "job11": 0,
    "job12": 45,
    "job13": 56,
    "job14": 0,
    "job15": 0,
    "job16": 0,
    "job17": 31,
    "job18": 0,
    "job19": 11,
    "job2": 0,
    "job20": 0,
    "job21": 72,
    "job22": 38,
    "job23": 36,
    "job24": 0,
    "job25": 8,
    "job26": 21,
    "job27": 1,
    "job28": 32,
    "job29": 62,
    "job3": 0,
    "job30": 8,
    "job31": 24,
    "job32": 70,
    "job33": 107,
    "job34": 116,
    "job35": 31,
    "job36": 76,
    "job37": 7,
    "job38": 62,
    "job39": 300,
    "job4": 0,
    "job40": 17,
    "job41": 619,
    "job42": 154,
    "job43": 194,
    "job44": 307,
    "job45": 75,
    "job46": 451,
    "job47": 584,
    "job48": 778,
    "job49": 234,
    "job5": 0,
    "job50": 27,
    "job6": 0,
    "job7": 0,
    "job8": 0,
    "job9": 0
}