{
    "1": 14,
    "10": 5546,
    "11": 3232,
    "12": 61,
    "13": 7063,
    "14": 6539,
    "15": 7032,
    "16": 5730,
    "17": 9515,
    "18": 6562,
    "19": 6051,
    "2": 21,
    "20": 5623,
    "21": 4973,
    "22": 18,
    "23": 7306,
    "24": 4890,
    "25": 3454,
    "26": 5,
    "27": 4359,
    "28": 3661,
    "29": 8415,
    "3": 34,
    "30": 3900,
    "31": 1806,
    "32": 361,
    "33": 3145,
    "34": 3403,
    "35": 10022,
    "36": 6811,
    "37": 7096,
    "38": 6538,
    "39": 9218,
    "4": 8338,
    "40": 4186,
    "41": 1836,
    "42": 5127,
    "43": 5546,
    "44": 8,
    "45": 8,
    "46": 8339,
    "47": 1872,
    "48": 12,
    "49": 3140,
    "5": 7235,
    "50": 5514,
    "6": 6710,
    "7": 4786,
    "8": 18,
    "9": 4931,
    "average": 4400.2
}