{
    "1": 39,
    "10": 54,
    "100": 8903,
    "11": 80,
    "12": 87,
    "13": 124,
    "14": 175,
    "15": 80,
    "16": 210,
    "17": 221,
    "18": 291,
    "19": 222,
    "2": 37,
    "20": 105,
    "21": 370,
    "22": 500,
    "23": 371,
    "24": 315,
    "25": 291,
    "26": 690,
    "27": 114,
    "28": 500,
    "29": 865,
    "3": 72,
    "30": 749,
    "31": 971,
    "32": 1209,
    "33": 930,
    "34": 1099,
    "35": 690,
    "36": 1284,
    "37": 1343,
    "38": 164,
    "39": 637,
    "4": 42,
    "40": 1279,
    "41": 2702,
    "42": 585,
    "43": 1247,
    "44": 520,
    "45": 256,
    "46": 5089,
    "47": 8095,
    "48": 9907,
    "49": 7465,
    "5": 54,
    "50": 6531,
    "51": 37,
    "52": 36,
    "53": 71,
    "54": 42,
    "55": 54,
    "56": 46,
    "57": 45,
    "58": 71,
    "59": 68,
    "6": 47,
    "60": 54,
    "61": 76,
    "62": 87,
    "63": 122,
    "64": 174,
    "65": 81,
    "66": 210,
    "67": 223,
    "68": 298,
    "69": 220,
    "7": 47,
    "70": 126,
    "71": 398,
    "72": 510,
    "73": 442,
    "74": 342,
    "75": 96,
    "76": 694,
    "77": 123,
    "78": 761,
    "79": 825,
    "8": 70,
    "80": 778,
    "81": 915,
    "82": 1157,
    "83": 330,
    "84": 976,
    "85": 681,
    "86": 1333,
    "87": 1361,
    "88": 261,
    "89": 976,
    "9": 70,
    "90": 1196,
    "91": 2658,
    "92": 429,
    "93": 2022,
    "94": 2853,
    "95": 2907,
    "96": 9577,
    "97": 8195,
    "98": 10553,
    "99": 1821
}