{
    "1": 39,
    "10": 52,
    "100": 9599.0,
    "11": 79,
    "12": 69.9,
    "13": 95,
    "14": 175,
    "15": 77,
    "16": 210,
    "17": 0,
    "18": 0,
    "19": 204.3,
    "2": 0,
    "20": 235,
    "21": 347.3,
    "22": 477.1,
    "23": 436,
    "24": 0,
    "25": 416.7,
    "26": 0,
    "27": 720.4,
    "28": 796,
    "29": 0,
    "3": 0,
    "30": 719.8,
    "31": 907.0,
    "32": 0,
    "33": 0,
    "34": 920.3,
    "35": 1034.2,
    "36": 1202.7,
    "37": 0,
    "38": 0,
    "39": 1179.7,
    "4": 42,
    "40": 1245.2,
    "41": 2665.4,
    "42": 1531.5,
    "43": 2609.2,
    "44": 0,
    "45": 2731.6,
    "46": 8568.6,
    "47": 9900.7,
    "48": 10372.5,
    "49": 3333.9,
    "5": 54,
    "50": 8221.0,
    "51": 36,
    "52": 0,
    "53": 0,
    "54": 0,
    "55": 54,
    "56": 9.0,
    "57": 47,
    "58": 0,
    "59": 72,
    "6": 0,
    "60": 54,
    "61": 0,
    "62": 58,
    "63": 104,
    "64": 0,
    "65": 0,
    "66": 108.3,
    "67": 0,
    "68": 0,
    "69": 0,
    "7": 0,
    "70": 235,
    "71": 365.3,
    "72": 297.1,
    "73": 0,
    "74": 458.4,
    "75": 454.7,
    "76": 668.4,
    "77": 660.4,
    "78": 421.7,
    "79": 0,
    "8": 0,
    "80": 730.8,
    "81": 890.0,
    "82": 0,
    "83": 1129.9,
    "84": 997.3,
    "85": 792.2,
    "86": 1217.7,
    "87": 1107.7,
    "88": 1216.9,
    "89": 1307.7,
    "9": 70,
    "90": 1227.2,
    "91": 0,
    "92": 2728.5,
    "93": 0,
    "94": 0,
    "95": 129.8,
    "96": 8256.6,
    "97": 3800.7,
    "98": 9999.5,
    "99": 8331.9
}