{
    "1": 0,
    "10": 0,
    "11": 0,
    "12": 0,
    "13": 0,
    "14": 0,
    "15": 0,
    "16": 0,
    "17": 0,
    "18": 79,
    "19": 0,
    "2": 0,
    "20": 0,
    "21": 0,
    "22": 0,
    "23": 0,
    "24": 0,
    "25": 35,
    "26": 0,
    "27": 0,
    "28": 0,
    "29": 0,
    "3": 0,
    "30": 0,
    "31": 0,
    "32": 1688,
    "33": 146,
    "34": 188,
    "35": 38,
    "36": 0,
    "37": 0,
    "38": 0,
    "39": 446,
    "4": 0,
    "40": 0,
    "41": 42,
    "42": 0,
    "43": 3153,
    "44": 89,
    "45": 0,
    "46": 116,
    "47": 283,
    "48": 0,
    "49": 115,
    "5": 0,
    "50": 63,
    "6": 0,
    "7": 0,
    "8": 0,
    "9": 0,
    "average": 129.62
}