{
    "1": [],
    "10": [],
    "100": [
        5,
        4
    ],
    "11": [],
    "12": [],
    "13": [],
    "14": [
        6
    ],
    "15": [],
    "16": [],
    "17": [],
    "18": [
        5
    ],
    "19": [],
    "2": [],
    "20": [
        2
    ],
    "21": [
        0,
        0
    ],
    "22": [
        7,
        5,
        5,
        7,
        4,
        7
    ],
    "23": [
        1,
        1
    ],
    "24": [
        10
    ],
    "25": [
        2
    ],
    "26": [],
    "27": [
        2
    ],
    "28": [
        7
    ],
    "29": [],
    "3": [],
    "30": [
        6,
        4
    ],
    "31": [],
    "32": [],
    "33": [
        11
    ],
    "34": [
        3,
        2
    ],
    "35": [
        2
    ],
    "36": [],
    "37": [
        6,
        6,
        6,
        31
    ],
    "38": [
        2
    ],
    "39": [
        5,
        4,
        30,
        5
    ],
    "4": [],
    "40": [],
    "41": [
        3,
        2,
        3,
        2
    ],
    "42": [
        10
    ],
    "43": [
        10,
        8,
        8,
        8
    ],
    "44": [
        7,
        8,
        40,
        6
    ],
    "45": [
        2
    ],
    "46": [
        12,
        9
    ],
    "47": [
        8,
        7
    ],
    "48": [
        7,
        5,
        4,
        7
    ],
    "49": [
        10,
        9
    ],
    "5": [],
    "50": [
        5,
        5
    ],
    "51": [],
    "52": [],
    "53": [],
    "54": [],
    "55": [],
    "56": [],
    "57": [],
    "58": [],
    "59": [],
    "6": [],
    "60": [],
    "61": [],
    "62": [],
    "63": [],
    "64": [],
    "65": [],
    "66": [],
    "67": [],
    "68": [
        5
    ],
    "69": [],
    "7": [],
    "70": [
        2
    ],
    "71": [],
    "72": [
        6,
        7,
        28,
        33
    ],
    "73": [],
    "74": [
        10
    ],
    "75": [
        2
    ],
    "76": [],
    "77": [
        2
    ],
    "78": [
        7
    ],
    "79": [
        9,
        9,
        37,
        65,
        7,
        15
    ],
    "8": [],
    "80": [],
    "81": [
        0,
        0,
        0,
        0
    ],
    "82": [],
    "83": [
        12
    ],
    "84": [
        3,
        2
    ],
    "85": [
        2
    ],
    "86": [],
    "87": [],
    "88": [
        2
    ],
    "89": [
        5
    ],
    "9": [],
    "90": [
        0,
        1
    ],
    "91": [
        3,
        3
    ],
    "92": [
        10
    ],
    "93": [
        8,
        9,
        65,
        8,
        7,
        8
    ],
    "94": [],
    "95": [
        2,
        2
    ],
    "96": [
        12,
        10
    ],
    "97": [
        9,
        8
    ],
    "98": [
        6,
        6,
        4,
        6,
        5,
        7
    ],
    "99": [
        10,
        9
    ]
}