{
    "job1": 0,
    "job10": 0,
    "job100": 173,
    "job11": 0,
    "job12": 0,
    "job13": 0,
    "job14": 22,
    "job15": 1,
    "job16": 0,
    "job17": 27,
    "job18": 0,
    "job19": 0,
    "job2": 0,
    "job20": 0,
    "job21": 46,
    "job22": 188,
    "job23": 47,
    "job24": 0,
    "job25": 3,
    "job26": 0,
    "job27": 11,
    "job28": 14,
    "job29": 0,
    "job3": 0,
    "job30": 0,
    "job31": 0,
    "job32": 76,
    "job33": 14,
    "job34": 23,
    "job35": 0,
    "job36": 27,
    "job37": 0,
    "job38": 10,
    "job39": 31,
    "job4": 0,
    "job40": 0,
    "job41": 293,
    "job42": 40,
    "job43": 87,
    "job44": 210,
    "job45": 28,
    "job46": 301,
    "job47": 294,
    "job48": 0,
    "job49": 92,
    "job5": 0,
    "job50": 187,
    "job51": 0,
    "job52": 0,
    "job53": 0,
    "job54": 0,
    "job55": 0,
    "job56": 0,
    "job57": 0,
    "job58": 0,
    "job59": 0,
    "job6": 0,
    "job60": 0,
    "job61": 0,
    "job62": 0,
    "job63": 0,
    "job64": 0,
    "job65": 0,
    "job66": 0,
    "job67": 0,
    "job68": 12,
    "job69": 19,
    "job7": 0,
    "job70": 1,
    "job71": 17,
    "job72": 211,
    "job73": 0,
    "job74": 26,
    "job75": 2,
    "job76": 0,
    "job77": 2,
    "job78": 11,
    "job79": 176,
    "job8": 0,
    "job80": 121,
    "job81": 209,
    "job82": 35,
    "job83": 27,
    "job84": 0,
    "job85": 5,
    "job86": 0,
    "job87": 19,
    "job88": 11,
    "job89": 203,
    "job9": 0,
    "job90": 94,
    "job91": 217,
    "job92": 116,
    "job93": 151,
    "job94": 121,
    "job95": 50,
    "job96": 317,
    "job97": 168,
    "job98": 345,
    "job99": 199
}