{
    "1": [],
    "10": [],
    "11": [],
    "12": [],
    "13": [],
    "14": [],
    "15": [
        34
    ],
    "16": [],
    "17": [],
    "18": [
        110
    ],
    "19": [],
    "2": [],
    "20": [
        34
    ],
    "21": [],
    "22": [
        146
    ],
    "23": [],
    "24": [
        170
    ],
    "25": [],
    "26": [],
    "27": [
        47
    ],
    "28": [
        180
    ],
    "29": [
        222
    ],
    "3": [],
    "30": [],
    "31": [],
    "32": [],
    "33": [
        184
    ],
    "34": [
        172,
        175
    ],
    "35": [
        33
    ],
    "36": [],
    "37": [],
    "38": [
        73
    ],
    "39": [
        146
    ],
    "4": [],
    "40": [
        78
    ],
    "41": [
        278,
        323
    ],
    "42": [
        232
    ],
    "43": [
        254,
        251
    ],
    "44": [
        272
    ],
    "45": [
        124
    ],
    "46": [
        590
    ],
    "47": [
        527
    ],
    "48": [
        582
    ],
    "49": [
        354
    ],
    "5": [],
    "50": [
        301
    ],
    "6": [],
    "7": [],
    "8": [],
    "9": []
}