{"job1": 0, "job45": 354, "job2": 0, "job3": 0, "job40": 73, "job15": 3, "job13": 13, "job37": 86, "job50": 301, "job39": 41, "job49": 301, "job44": 193, "job32": 46, "job25": 13, "job6": 0, "job12": 2, "job43": 674, "job35": 9, "job29": 148, "job7": 0, "job46": 300, "job23": 57, "job47": 2440, "job34": 115, "job21": 34, "job33": 127, "job36": 130, "job24": 70, "job28": 76, "job48": 156, "job17": 34, "job8": 0, "job30": 24, "job41": 161, "job16": 8, "job27": 3, "job20": 19, "job38": 119, "job11": 76, "job42": 133, "job10": 21, "job22": 20, "job4": 0, "job18": 14, "job19": 47, "job5": 0, "job9": 0, "job26": 37, "job31": 83, "job14": 62}