{
    "1": 28,
    "10": 29,
    "100": 1926,
    "11": 14,
    "12": 444,
    "13": 184,
    "14": 33,
    "15": 317,
    "16": 17,
    "17": 335,
    "18": 3304,
    "19": 3650,
    "2": 3499,
    "20": 733,
    "21": 10,
    "22": 29,
    "23": 10,
    "24": 2704,
    "25": 30,
    "26": 290,
    "27": 495,
    "28": 7,
    "29": 3278,
    "3": 2,
    "30": 3147,
    "31": 2201,
    "32": 1224,
    "33": 3116,
    "34": 3327,
    "35": 1921,
    "36": 2798,
    "37": 40,
    "38": 1547,
    "39": 11,
    "4": 31,
    "40": 1246,
    "41": 1012,
    "42": 11,
    "43": 210,
    "44": 622,
    "45": 40,
    "46": 8,
    "47": 587,
    "48": 584,
    "49": 986,
    "5": 2658,
    "50": 14,
    "51": 13,
    "52": 1218,
    "53": 1212,
    "54": 606,
    "55": 1242,
    "56": 18,
    "57": 1195,
    "58": 651,
    "59": 2755,
    "6": 3814,
    "60": 3,
    "61": 633,
    "62": 611,
    "63": 471,
    "64": 634,
    "65": 47,
    "66": 33,
    "67": 148,
    "68": 26,
    "69": 1241,
    "7": 15,
    "70": 2,
    "71": 676,
    "72": 3,
    "73": 1279,
    "74": 33,
    "75": 603,
    "76": 3465,
    "77": 12,
    "78": 20,
    "79": 13,
    "8": 19,
    "80": 2797,
    "81": 314,
    "82": 3638,
    "83": 1882,
    "84": 1,
    "85": 1285,
    "86": 1223,
    "87": 621,
    "88": 18,
    "89": 646,
    "9": 3572,
    "90": 26,
    "91": 41,
    "92": 3590,
    "93": 445,
    "94": 3974,
    "95": 4015,
    "96": 3331,
    "97": 24,
    "98": 16,
    "99": 5,
    "average": 1028.84
}