{
    "1": 0,
    "10": 0,
    "11": 0,
    "12": 0,
    "13": 0,
    "14": 78,
    "15": 44,
    "16": 0,
    "17": 0,
    "18": 79,
    "19": 0,
    "2": 0,
    "20": 140,
    "21": 0,
    "22": 164,
    "23": 47,
    "24": 0,
    "25": 42,
    "26": 0,
    "27": 63,
    "28": 114,
    "29": 276,
    "3": 0,
    "30": 81,
    "31": 49,
    "32": 669,
    "33": 469,
    "34": 140,
    "35": 234,
    "36": 24,
    "37": 246,
    "38": 250,
    "39": 324,
    "4": 0,
    "40": 98,
    "41": 397,
    "42": 468,
    "43": 125,
    "44": 609,
    "45": 315,
    "46": 923,
    "47": 663,
    "48": 605,
    "49": 661,
    "5": 0,
    "50": 375,
    "6": 0,
    "7": 0,
    "8": 0,
    "9": 0,
    "average": 175.44
}